src/pc_file.v
module pc_file(
    input wire          clk,      // Clock Signal
    input wire          a_rst,    // Async Reset
    input wire          r_ts,     // Read Task Selector
    input wire          w_ts,     // Write Task Selector
    input wire          ws,       // Write Select
    input wire          hold,     // Hold Value
    input wire[15:0]    i_pc,     // New PC value
    output wire[15:0]   o_pc,     // Next Instruction Address
    output wire[15:0]   o_prev_pc // Previus PC (for use in decode stage)
);

reg[14:0] pc_0;
reg[14:0] pc_1;

reg prev_pc_ts;

reg[15:0] pc_next;

wire[14:0] selected = ( r_ts ? pc_1 : pc_0 );

always @(*) begin
    pc_next = selected + 1'b1;
end

always @(posedge clk) begin
    prev_pc_ts <= r_ts;
end

// PC 0
always @(posedge clk or negedge a_rst) begin
    if (~a_rst) begin
        pc_0 <= 15'h7FFF;
    end else begin
        case ({hold, ws & ~w_ts})
        2'b00: pc_0 <= pc_next;
        2'b01: pc_0 <= i_pc[15:1];
        2'b10: pc_0 <= pc_0;
        2'b11: pc_0 <= pc_0;
        endcase
    end
end

// PC 1
always @(posedge clk) begin
    case ({hold, ws & w_ts})
    2'b00: pc_1 <= pc_next;
    2'b01: pc_1 <= i_pc[15:1];
    2'b10: pc_1 <= pc_1;
    2'b11: pc_1 <= pc_1;
    endcase
end

assign o_pc = { pc_next, 1'b0 };
assign o_prev_pc = { prev_pc_ts ? pc_1 : pc_0, 1'b0 };

endmodule

test/tb_pc_file.v

module tb_pc_file;

reg clk;
reg a_rst;

reg[15:0] npc;
reg hold;
reg r_ts;
reg w_ts;
reg ws;

wire[15:0] pc_val;
wire[15:0] prev_pc_val;

pc_file pc(
    .clk (clk),    // Clock Signal
    .a_rst (a_rst),    // Async Reset
    .r_ts (r_ts),
    .w_ts (w_ts),
    .ws (ws),
    .hold (hold),
    .i_pc (npc),
    .o_pc (pc_val),
    .o_prev_pc (prev_pc_val)
);

initial begin
    $dumpfile("dumps/tb_pc_file_dump.vcd");
    $dumpvars(0, tb_pc_file);
    clk = 0;
    a_rst = 0;
    npc = 15'h4FF0;
    hold = 1;
    r_ts = 0;
    w_ts = 0;
    ws = 0;
    #1 a_rst = 1;
    #3
    hold = 0;
    #4
    ws = 1;
    #4
    hold = 1;
    #4
    ws = 0;
    #4
    hold = 0;
    #18
    $finish();
end

always begin
    #2 clk <= ~clk;
end

endmodule

dumps/tb_pc_file_dump.vcd
$date
	Wed Oct  9 01:19:58 2019
$end
$version
	Icarus Verilog
$end
$timescale
	1s
$end
$scope module tb_pc_file $end
$var wire 16 ! prev_pc_val [15:0] $end
$var wire 16 " pc_val [15:0] $end
$var reg 1 # a_rst $end
$var reg 1 $ clk $end
$var reg 1 % hold $end
$var reg 16 & npc [15:0] $end
$var reg 1 ' r_ts $end
$var reg 1 ( w_ts $end
$var reg 1 ) ws $end
$scope module pc $end
$var wire 1 # a_rst $end
$var wire 1 $ clk $end
$var wire 1 % hold $end
$var wire 16 * i_pc [15:0] $end
$var wire 1 ' r_ts $end
$var wire 1 ( w_ts $end
$var wire 1 ) ws $end
$var wire 15 + selected [14:0] $end
$var wire 16 , o_prev_pc [15:0] $end
$var wire 16 - o_pc [15:0] $end
$var reg 15 . pc_0 [14:0] $end
$var reg 15 / pc_1 [14:0] $end
$var reg 16 0 pc_next [15:0] $end
$var reg 1 1 prev_pc_ts $end
$upscope $end
$upscope $end
$enddefinitions $end
#0
$dumpvars
x1
b1000000000000000 0
bx /
b111111111111111 .
b0 -
bx0 ,
b111111111111111 +
b100111111110000 *
0)
0(
0'
b100111111110000 &
1%
0$
0#
b0 "
bx0 !
$end
#1
1#
#2
b1111111111111110 !
b1111111111111110 ,
01
1$
#4
0$
0%
#6
b10 "
b10 -
b1 0
b0 +
b0 !
b0 ,
b0 /
b0 .
1$
#8
0$
1)
#10
b100111111110010 "
b100111111110010 -
b10011111111001 0
b10011111111000 +
b100111111110000 !
b100111111110000 ,
b1 /
b10011111111000 .
1$
#12
0$
1%
#14
1$
#16
0$
0)
#18
1$
#20
0$
0%
#22
b100111111110100 "
b100111111110100 -
b10011111111010 0
b10011111111001 +
b100111111110010 !
b100111111110010 ,
b10011111111001 /
b10011111111001 .
1$
#24
0$
#26
b100111111110110 "
b100111111110110 -
b10011111111011 0
b10011111111010 +
b100111111110100 !
b100111111110100 ,
b10011111111010 /
b10011111111010 .
1$
#28
0$
#30
b100111111111000 "
b100111111111000 -
b10011111111100 0
b10011111111011 +
b100111111110110 !
b100111111110110 ,
b10011111111011 /
b10011111111011 .
1$
#32
0$
#34
b100111111111010 "
b100111111111010 -
b10011111111101 0
b10011111111100 +
b100111111111000 !
b100111111111000 ,
b10011111111100 /
b10011111111100 .
1$
#36
0$
#38
b100111111111100 "
b100111111111100 -
b10011111111110 0
b10011111111101 +
b100111111111010 !
b100111111111010 ,
b10011111111101 /
b10011111111101 .
1$
